cloudshell/__init__.py
cloudshell/shell/__init__.py
cloudshell/shell/standards/__init__.py
cloudshell/shell/standards/networking/__init__.py
cloudshell/shell/standards/networking/autoload_model.py
cloudshell/shell/standards/networking/driver_interface.py
cloudshell/shell/standards/networking/resource_config.py
tests/__init__.py
tests/conftest.py
tests/cloudshell/__init__.py
tests/cloudshell/shell_networking_standards/__init__.py
tests/cloudshell/shell_networking_standards/test_autoload_generic_models.py
tests/cloudshell/shell_networking_standards/test_driver_interface.py
tests/cloudshell/shell_networking_standards/test_resource_config.py
cloudshell_shell_networking_standard-6.0.0.dist-info/LICENSE.htm
cloudshell_shell_networking_standard-6.0.0.dist-info/METADATA
cloudshell_shell_networking_standard-6.0.0.dist-info/WHEEL
cloudshell_shell_networking_standard-6.0.0.dist-info/top_level.txt
cloudshell_shell_networking_standard-6.0.0.dist-info/RECORD
